{
  "appid": "1048250",
  "public_only": "1",
  "common": {
    "name": "Bowlbo: The Quest for Bing Bing",
    "type": "Game",
    "releasestate": "prerelease",
    "oslist": "windows",
    "osarch": "64",
    "osextended": "",
    "logo": "34534f52e9b5e24e6725ee8c7eceba24f4da7e14",
    "logo_small": "34534f52e9b5e24e6725ee8c7eceba24f4da7e14_thumb",
    "icon": "a7ec25804542f63d99ae0fc71e002cbaf2c1cacd",
    "clienttga": "f063c634a5ec2f3a79065fb9509ffb6c367aa4a4",
    "clienticon": "b939515384576b2d2d97f1a5b3e0dd68ca61258b",
    "content_descriptors": {
      "0": "2",
      "1": "5"
    },
    "restricted_countries": "DE",
    "metacritic_name": "Bowlbo: The Quest for Bing Bing",
    "controller_support": "full",
    "small_capsule": {
      "english": "capsule_231x87.jpg"
    },
    "header_image": {
      "english": "header.jpg"
    },
    "library_assets": {
      "library_capsule": "en",
      "library_hero": "en",
      "library_logo": "en",
      "logo_position": {
        "pinned_position": "BottomCenter",
        "width_pct": "41.31072003854024",
        "height_pct": "56.98303385313598"
      }
    },
    "library_assets_full": {
      "library_capsule": {
        "image": {
          "english": "library_600x900.jpg"
        },
        "image2x": {
          "english": "library_600x900_2x.jpg"
        }
      },
      "library_hero": {
        "image": {
          "english": "library_hero.jpg"
        }
      },
      "library_logo": {
        "logo_position": {
          "pinned_position": "BottomCenter",
          "width_pct": "41.31072003854024",
          "height_pct": "56.98303385313598"
        },
        "image": {
          "english": "logo.png"
        },
        "image2x": {
          "english": "logo_2x.png"
        }
      }
    },
    "store_asset_mtime": "1583382317",
    "associations": {
      "0": {
        "type": "developer",
        "name": "OneyWare"
      },
      "1": {
        "type": "publisher",
        "name": "OneyWare"
      }
    },
    "primary_genre": "25",
    "genres": {
      "0": "1",
      "1": "25",
      "2": "23"
    },
    "category": {
      "category_2": "1",
      "category_28": "1",
      "category_22": "1"
    },
    "supported_languages": {
      "english": {
        "supported": "true",
        "subtitles": "true"
      }
    },
    "community_hub_visible": "1",
    "gameid": "1048250",
    "exfgls": "8",
    "content_descriptors_including_dlc": {
      "0": "2",
      "1": "5"
    },
    "store_tags": {
      "0": "492",
      "1": "21",
      "2": "19",
      "3": "4136",
      "4": "3798",
      "5": "1625",
      "6": "4345",
      "7": "1721",
      "8": "4667",
      "9": "1719",
      "10": "3965",
      "11": "5411",
      "12": "12095",
      "13": "1667",
      "14": "9130"
    }
  }
}