{
  "appid": "1448320",
  "common": {
    "name": "Boat Warfare",
    "type": "Game",
    "icon": "f2c62f7d5075209b2fbde9fe97a3c3559dc31608",
    "logo": "f8622e7317169c1368a3c516f6773ff2a414daf0",
    "logo_small": "f8622e7317169c1368a3c516f6773ff2a414daf0_thumb",
    "oslist": "windows",
    "osarch": "",
    "osextended": "",
    "clienttga": "c44f0faa1d63dde0d91cbe53d94becee9445a8b5",
    "clienticon": "839bd4fd28b5f75b9d0c37c6bc791b19174ff666",
    "releasestate": "released",
    "controllertagwizard": "1",
    "controller_support": "partial",
    "small_capsule": {
      "english": "a375d652b7c60e434fc19a2080ddb47664fe3baf/capsule_231x87.jpg"
    },
    "header_image": {
      "english": "2da6a72a17591bbfc6477c18000c0a23f19d2d9f/header.jpg"
    },
    "library_assets": {
      "library_capsule": "en",
      "library_hero": "en",
      "library_hero_blur": "en",
      "library_logo": "en",
      "library_header": "en",
      "logo_position": {
        "pinned_position": "CenterCenter",
        "width_pct": "62.98020954598374",
        "height_pct": "100"
      }
    },
    "library_assets_full": {
      "library_capsule": {
        "image": {
          "english": "d078cf0dbaebdf99606c79df3edd2863af027d12/library_600x900.jpg"
        },
        "image2x": {
          "english": "d078cf0dbaebdf99606c79df3edd2863af027d12/library_600x900_2x.jpg"
        }
      },
      "library_hero": {
        "image": {
          "english": "3b2217405d8f811559cc75f7fb3f31618a3bf017/library_hero.jpg"
        },
        "image2x": {
          "english": "3b2217405d8f811559cc75f7fb3f31618a3bf017/library_hero_2x.jpg"
        }
      },
      "library_hero_blur": {
        "image": {
          "english": "3b2217405d8f811559cc75f7fb3f31618a3bf017/library_hero_blur.jpg"
        }
      },
      "library_logo": {
        "logo_position": {
          "pinned_position": "CenterCenter",
          "width_pct": "62.98020954598374",
          "height_pct": "100"
        },
        "image": {
          "english": "logo.png"
        },
        "image2x": {
          "english": "logo_2x.png"
        }
      },
      "library_header": {
        "image": {
          "english": "2da6a72a17591bbfc6477c18000c0a23f19d2d9f/library_header.jpg"
        },
        "image2x": {
          "english": "2da6a72a17591bbfc6477c18000c0a23f19d2d9f/library_header_2x.jpg"
        }
      }
    },
    "store_asset_mtime": "1753327366",
    "associations": {
      "0": {
        "type": "developer",
        "name": "Ty Victorson"
      },
      "1": {
        "type": "publisher",
        "name": "Ty Victorson"
      }
    },
    "primary_genre": "1",
    "genres": {
      "0": "1",
      "1": "25",
      "2": "23"
    },
    "category": {
      "category_2": "1",
      "category_18": "1",
      "category_22": "1",
      "category_15": "1",
      "category_62": "1"
    },
    "supported_languages": {
      "english": {
        "supported": "true",
        "full_audio": "true"
      }
    },
    "steam_release_date": "1625158925",
    "community_visible_stats": "1",
    "community_hub_visible": "1",
    "gameid": "1448320",
    "store_tags": {
      "0": "19",
      "1": "492",
      "2": "4182",
      "3": "1774",
      "4": "3814",
      "5": "4191",
      "6": "1697",
      "7": "4598",
      "8": "4295",
      "9": "5673",
      "10": "21",
      "11": "1678",
      "12": "3993",
      "13": "11104"
    }
  },
  "extended": {
    "developer": "Ty Victorson",
    "publisher": "Ty Victorson"
  },
  "config": {
    "installdir": "Boat Warfare",
    "launch": {
      "0": {
        "executable": "BOAT WARFARE.exe",
        "type": "default",
        "config": {
          "oslist": "windows"
        }
      }
    }
  },
  "depots": {
    "1448321": {
      "config": {
        "language": "english",
        "oslist": "windows"
      },
      "manifests": {
        "public": {
          "gid": "1213890498650558264",
          "size": "3195070261",
          "download": "994404576"
        }
      }
    },
    "branches": {
      "public": {
        "buildid": "20399800",
        "timeupdated": "1760520489"
      }
    },
    "privatebranches": "1"
  }
}