{
  "appid": "2485190",
  "common": {
    "name": "MediBang Paint for Desktop",
    "type": "Application",
    "releasestate": "released",
    "oslist": "windows,macos",
    "osarch": "64",
    "osextended": "macos64,macosapplesilicon",
    "icon": "c93f214f8083531da20b4fab89b8aa87dddf8308",
    "clienticon": "71c169f68e2f6824e831db1c57853aace1e9bce3",
    "clienttga": "cfd8780cda64ab95676bbac5cd9157b29d71759d",
    "eulas": {
      "0": {
        "id": "2485190_eula_0",
        "name": "MediBang Paint for Steam EULA",
        "url": "https://store.steampowered.com//eula/2485190_eula_0",
        "version": "8"
      }
    },
    "small_capsule": {
      "english": "2922eace500cea835a744000921cde0c5e076b06/capsule_231x87.jpg"
    },
    "header_image": {
      "english": "d0cf729458a34394a6be439608f9790190e988b7/header.jpg"
    },
    "library_assets": {
      "library_capsule": "en",
      "library_hero": "en",
      "library_logo": "en",
      "library_header": "en",
      "logo_position": {
        "pinned_position": "BottomLeft",
        "width_pct": "51.51338766006985",
        "height_pct": "27.20324141411143"
      }
    },
    "library_assets_full": {
      "library_capsule": {
        "image": {
          "english": "59fa4f3177b0c8311ca53f9e32c069b0f3698b72/library_600x900.jpg"
        },
        "image2x": {
          "english": "59fa4f3177b0c8311ca53f9e32c069b0f3698b72/library_600x900_2x.jpg"
        }
      },
      "library_hero": {
        "image": {
          "english": "library_hero.jpg"
        },
        "image2x": {
          "english": "library_hero_2x.jpg"
        }
      },
      "library_logo": {
        "image": {
          "english": "276224a786a07155a0bd2343ffc5f4346843b978/logo.png"
        },
        "image2x": {
          "english": "276224a786a07155a0bd2343ffc5f4346843b978/logo_2x.png"
        },
        "logo_position": {
          "pinned_position": "BottomLeft",
          "width_pct": "51.51338766006985",
          "height_pct": "27.20324141411143"
        }
      },
      "library_header": {
        "image": {
          "english": "d0cf729458a34394a6be439608f9790190e988b7/library_header.jpg"
        },
        "image2x": {
          "english": "d0cf729458a34394a6be439608f9790190e988b7/library_header_2x.jpg"
        }
      }
    },
    "store_asset_mtime": "1754451828",
    "associations": {
      "0": {
        "type": "developer",
        "name": "MediBang Inc."
      },
      "1": {
        "type": "publisher",
        "name": "MediBang Inc."
      }
    },
    "primary_genre": "53",
    "genres": {
      "0": "51",
      "1": "53",
      "2": "55"
    },
    "category": {},
    "supported_languages": {
      "english": {
        "supported": "true"
      },
      "japanese": {
        "supported": "true"
      },
      "koreana": {
        "supported": "true"
      },
      "brazilian": {
        "supported": "true"
      },
      "russian": {
        "supported": "true"
      },
      "schinese": {
        "supported": "true"
      },
      "latam": {
        "supported": "true"
      },
      "tchinese": {
        "supported": "true"
      }
    },
    "steam_release_date": "1690790579",
    "community_hub_visible": "1",
    "gameid": "2485190",
    "exfgls": "6",
    "store_tags": {
      "0": "84",
      "1": "809",
      "2": "872",
      "3": "8013"
    },
    "review_score": "5",
    "review_percentage": "63"
  },
  "extended": {
    "developer": "MediBang Inc.",
    "publisher": "MediBang Inc."
  },
  "config": {
    "installdir": "MediBang Paint",
    "launch": {
      "0": {
        "executable": "MediBangPaintPro.exe",
        "type": "default",
        "config": {
          "oslist": "windows",
          "osarch": "64"
        }
      },
      "1": {
        "executable": "MediBangPaintPro.app",
        "type": "default",
        "config": {
          "oslist": "macos"
        }
      }
    }
  },
  "depots": {
    "228989": {
      "config": {
        "oslist": "windows"
      },
      "depotfromapp": "228980",
      "sharedinstall": "1"
    },
    "2485191": {
      "config": {
        "osarch": "64",
        "oslist": "windows"
      },
      "manifests": {
        "public": {
          "gid": "4263934761868668256",
          "size": "97208311",
          "download": "32900304"
        }
      }
    },
    "2485192": {
      "config": {
        "oslist": "macos",
        "osarch": "64"
      },
      "manifests": {
        "public": {
          "gid": "2426569001678396044",
          "size": "91687634",
          "download": "33016688"
        }
      }
    },
    "baselanguages": "english,koreana,spanish,schinese,tchinese,japanese,portuguese",
    "workshopdepot": "2485190",
    "branches": {
      "public": {
        "buildid": "19238390",
        "timeupdated": "1753234586"
      }
    },
    "privatebranches": "1"
  },
  "ufs": {
    "quota": "0",
    "maxnumfiles": "0"
  }
}