{
  "appid": "2497380",
  "common": {
    "name": "Brightstone Mysteries: The Others",
    "type": "Game",
    "releasestate": "released",
    "oslist": "windows,macos,linux",
    "osarch": "",
    "osextended": "macos64,macosapplesilicon,macosnotarized",
    "clienticon": "fb690a0190031c521966724fc661d2caab6e0b0d",
    "clienttga": "9b791da0e4560e99de8a1b466ac36838ba386405",
    "icon": "85b372ce60c89925084582399ace883d4b0662e9",
    "clienticns": "bd8a140a5418342ac6d2371a608d3b41790940dd",
    "linuxclienticon": "e08fba7ecd183c2d7e212dac3f9d8195f3d329f2",
    "small_capsule": {
      "english": "capsule_231x87.jpg"
    },
    "header_image": {
      "english": "header.jpg"
    },
    "library_assets": {
      "library_capsule": "en",
      "library_hero": "en",
      "library_logo": "en",
      "logo_position": {
        "pinned_position": "BottomLeft",
        "width_pct": "54.805491990846676",
        "height_pct": "75.07598667893863"
      }
    },
    "library_assets_full": {
      "library_capsule": {
        "image": {
          "english": "library_600x900.jpg"
        },
        "image2x": {
          "english": "library_600x900_2x.jpg"
        }
      },
      "library_hero": {
        "image": {
          "english": "library_hero.jpg"
        },
        "image2x": {
          "english": "library_hero_2x.jpg"
        }
      },
      "library_logo": {
        "image": {
          "english": "logo.png"
        },
        "image2x": {
          "english": "logo_2x.png"
        },
        "logo_position": {
          "pinned_position": "BottomLeft",
          "width_pct": "54.805491990846676",
          "height_pct": "75.07598667893863"
        }
      }
    },
    "store_asset_mtime": "1691136639",
    "associations": {
      "0": {
        "type": "developer",
        "name": "Cateia Games"
      },
      "1": {
        "type": "publisher",
        "name": "Cateia Games"
      },
      "2": {
        "type": "franchise",
        "name": "Brightstone Mysteries"
      }
    },
    "primary_genre": "25",
    "genres": {
      "0": "25",
      "1": "23"
    },
    "category": {
      "category_2": "1",
      "category_23": "1",
      "category_68": "1",
      "category_74": "1",
      "category_76": "1",
      "category_77": "1",
      "category_78": "1",
      "category_79": "1",
      "category_62": "1"
    },
    "supported_languages": {
      "english": {
        "supported": "true",
        "full_audio": "true",
        "subtitles": "true"
      },
      "french": {
        "supported": "true",
        "subtitles": "true"
      },
      "italian": {
        "supported": "true",
        "subtitles": "true"
      },
      "german": {
        "supported": "true",
        "subtitles": "true"
      },
      "spanish": {
        "supported": "true",
        "subtitles": "true"
      },
      "dutch": {
        "supported": "true",
        "subtitles": "true"
      },
      "portuguese": {
        "supported": "true",
        "subtitles": "true"
      }
    },
    "steam_release_date": "1692201969",
    "community_visible_stats": "1",
    "community_hub_visible": "1",
    "gameid": "2497380",
    "store_tags": {
      "0": "21",
      "1": "1698",
      "2": "1664",
      "3": "3799",
      "4": "3834",
      "5": "1738",
      "6": "3871",
      "7": "4305",
      "8": "4166",
      "9": "5372",
      "10": "4604",
      "11": "5613",
      "12": "1684",
      "13": "8369",
      "14": "5716",
      "15": "3942",
      "16": "7208",
      "17": "1742",
      "18": "4182",
      "19": "492"
    }
  },
  "extended": {
    "developer": "Cateia Games",
    "publisher": "Cateia Games",
    "homepage": "https://cateia.com/game/brightstone-mysteries-the-others/"
  },
  "config": {
    "installdir": "Brightstone Mysteries - The Others",
    "launch": {
      "0": {
        "executable": "others.exe",
        "type": "default",
        "config": {
          "oslist": "windows"
        }
      },
      "1": {
        "executable": "others_mac_steam.app",
        "type": "default",
        "config": {
          "oslist": "macos"
        }
      },
      "2": {
        "executable": "others_steam_linux_x64",
        "type": "default",
        "config": {
          "oslist": "linux"
        }
      }
    }
  },
  "depots": {
    "2497381": {
      "config": {
        "oslist": "windows"
      },
      "manifests": {
        "public": {
          "gid": "7353438038506575970",
          "size": "1123216901",
          "download": "620245424"
        }
      }
    },
    "2497382": {
      "config": {
        "oslist": "macos"
      },
      "manifests": {
        "public": {
          "gid": "2269474080677697817",
          "size": "1159159775",
          "download": "631724080"
        }
      }
    },
    "2497383": {
      "config": {
        "oslist": "linux"
      },
      "manifests": {
        "public": {
          "gid": "228917892174475106",
          "size": "1021613069",
          "download": "510220560"
        }
      }
    },
    "baselanguages": "english,german,french,italian,spanish,portuguese,dutch",
    "branches": {
      "public": {
        "buildid": "13044753",
        "timeupdated": "1703544784"
      }
    },
    "privatebranches": "1"
  },
  "ufs": {
    "quota": "10000000000",
    "maxnumfiles": "1000",
    "savefiles": {
      "0": {
        "root": "WinAppDataLocalLow",
        "path": "Cateia Games/Brightstone Mysteries - The Others",
        "pattern": "*.xml",
        "recursive": "1"
      }
    },
    "rootoverrides": {
      "0": {
        "root": "WinAppDataLocalLow",
        "os": "MacOS",
        "oscompare": "=",
        "useinstead": "MacAppSupport",
        "pathtransforms": {
          "0": {
            "find": "Cateia Games/Brightstone Mysteries - The Others",
            "replace": "com.paprikari.theothers"
          }
        }
      },
      "1": {
        "root": "WinAppDataLocalLow",
        "os": "Linux",
        "oscompare": "=",
        "useinstead": "LinuxXdgConfigHome",
        "addpath": "unity3d/"
      }
    }
  }
}