{
  "appid": "3364080",
  "public_only": "1",
  "common": {
    "name": "Blessing In The Darkness",
    "type": "Game",
    "releasestate": "prerelease",
    "icon": "6fabd111ec159e4c49b0975e9ec8a5b8512a6b2d",
    "clienttga": "36bd1661f65dc4b256c07dc65c8f5671aa53f56f",
    "clienticon": "031df5795fad5c4ea208d095ba7d984be0872922",
    "oslist": "windows",
    "osarch": "",
    "osextended": "",
    "controllertagwizard": "1",
    "controller_support": "full",
    "small_capsule": {
      "english": "2bb570f088997c64995f0d0c2c708b351eb99da1/capsule_231x87.jpg"
    },
    "header_image": {
      "english": "6611f066145c756e2cbb408bfc2953d415dd7979/header.jpg"
    },
    "library_assets": {
      "library_capsule": "en",
      "library_hero": "en",
      "library_hero_blur": "en",
      "library_logo": "en",
      "library_header": "en",
      "logo_position": {
        "pinned_position": "BottomLeft",
        "width_pct": "100",
        "height_pct": "100"
      }
    },
    "library_assets_full": {
      "library_capsule": {
        "image": {
          "english": "381b5928f553db54ed94b71fe43c5df2c6d61bd6/library_capsule.jpg"
        },
        "image2x": {
          "english": "381b5928f553db54ed94b71fe43c5df2c6d61bd6/library_capsule_2x.jpg"
        }
      },
      "library_hero": {
        "image2x": {
          "english": "81e480aa095006fa33a9dc39e34785b7c3df8abe/library_hero_2x.jpg"
        },
        "image": {
          "english": "81e480aa095006fa33a9dc39e34785b7c3df8abe/library_hero.jpg"
        }
      },
      "library_hero_blur": {
        "image": {
          "english": "81e480aa095006fa33a9dc39e34785b7c3df8abe/library_hero_blur.jpg"
        }
      },
      "library_logo": {
        "image": {
          "english": "06d9bf261e063b61010a620bba8ac7482ae70373/logo.png"
        },
        "image2x": {
          "english": "06d9bf261e063b61010a620bba8ac7482ae70373/logo_2x.png"
        },
        "logo_position": {
          "pinned_position": "BottomLeft",
          "width_pct": "100",
          "height_pct": "100"
        }
      },
      "library_header": {
        "image": {
          "english": "6611f066145c756e2cbb408bfc2953d415dd7979/library_header.jpg"
        },
        "image2x": {
          "english": "6611f066145c756e2cbb408bfc2953d415dd7979/library_header_2x.jpg"
        }
      }
    },
    "store_asset_mtime": "1761620765",
    "associations": {
      "0": {
        "type": "developer",
        "name": "Oldbookstudio"
      },
      "1": {
        "type": "publisher",
        "name": "Oldbookstudio"
      }
    },
    "primary_genre": "23",
    "genres": {
      "0": "1",
      "1": "4",
      "2": "23",
      "3": "3",
      "4": "2"
    },
    "category": {
      "category_2": "1",
      "category_28": "1",
      "category_55": "1",
      "category_56": "1",
      "category_57": "1",
      "category_58": "1",
      "category_62": "1"
    },
    "supported_languages": {
      "english": {
        "supported": "true",
        "subtitles": "true"
      },
      "brazilian": {
        "supported": "true",
        "subtitles": "true"
      }
    },
    "community_hub_visible": "1",
    "gameid": "3364080",
    "exfgls": "8",
    "store_tags": {
      "0": "1720",
      "1": "4604",
      "2": "1741",
      "3": "1667",
      "4": "4325",
      "5": "4026",
      "6": "4184",
      "7": "3964",
      "8": "492",
      "9": "122",
      "10": "14139",
      "11": "3952",
      "12": "4252",
      "13": "4166",
      "14": "4172",
      "15": "9",
      "16": "9541",
      "17": "4342",
      "18": "3959",
      "19": "4182"
    }
  }
}