{
  "appid": "3371510",
  "common": {
    "name": "Roulette Hero",
    "type": "Game",
    "releasestate": "released",
    "name_localized": {
      "english": "Roulette Hero",
      "schinese": "轮盘英雄",
      "tchinese": "輪盤英雄",
      "japanese": "Roulette Hero"
    },
    "languages": {
      "english": "1",
      "schinese": "1",
      "tchinese": "1",
      "japanese": "1"
    },
    "icon": "a38a6c187fbd4ccf1828c15640ac06de7cf9a438",
    "clienttga": "121489f83bec6e846024e9fde89d11f8cb0d1fd7",
    "clienticon": "4c32e9344e401209ff4d55f200401f85d19a471e",
    "oslist": "windows",
    "osarch": "",
    "osextended": "",
    "controllertagwizard": "1",
    "small_capsule": {
      "english": "14fcf8e290d9d56f7b8340c5678c6524894c9e69/capsule_231x87.jpg",
      "schinese": "587d56a495dc7dd1a649d877e174fc5304c19a12/capsule_231x87_schinese.jpg"
    },
    "header_image": {
      "schinese": "40ba56f4964ec808c2abeb3e27ff1ca068aa38bf/header_schinese.jpg",
      "english": "d8f4a3b61bf07def68ef77a2aab4d5d1fe8c1ff7/header.jpg"
    },
    "library_assets": {
      "library_capsule": "zh-cn,en",
      "library_hero": "en",
      "library_hero_blur": "en,zh-cn",
      "library_logo": "en,zh-cn",
      "library_header": "zh-cn,en",
      "logo_position": {
        "pinned_position": "CenterCenter",
        "width_pct": "44.86795014742938",
        "height_pct": "46.518377793609346"
      }
    },
    "library_assets_full": {
      "library_capsule": {
        "image": {
          "schinese": "dd734d6f82fe415f339f9331c3aa9e727e120b62/library_capsule_schinese.jpg",
          "english": "3b2a383549bff37d35db327d78cef58b463a3dea/library_capsule.jpg"
        },
        "image2x": {
          "schinese": "dd734d6f82fe415f339f9331c3aa9e727e120b62/library_capsule_schinese_2x.jpg",
          "english": "3b2a383549bff37d35db327d78cef58b463a3dea/library_capsule_2x.jpg"
        }
      },
      "library_hero": {
        "image2x": {
          "english": "0a59f8ff51d096fef7ef34c67b1689f57d749f4a/library_hero_2x.jpg"
        },
        "image": {
          "english": "0a59f8ff51d096fef7ef34c67b1689f57d749f4a/library_hero.jpg"
        }
      },
      "library_hero_blur": {
        "image": {
          "english": "0a59f8ff51d096fef7ef34c67b1689f57d749f4a/library_hero_blur.jpg",
          "schinese": "d26510173fa8972bc17c0bd23efc7bcb48b13c0c/library_hero_blur_schinese.jpg"
        }
      },
      "library_logo": {
        "image": {
          "english": "e6ccc73dbcca8f483dcff606e847afb8354bf81d/logo.png",
          "schinese": "25366c729a1c3934b38bfbfdf35ed844ba3f98c5/logo_schinese.png"
        },
        "image2x": {
          "english": "e6ccc73dbcca8f483dcff606e847afb8354bf81d/logo_2x.png",
          "schinese": "25366c729a1c3934b38bfbfdf35ed844ba3f98c5/logo_schinese_2x.png"
        },
        "logo_position": {
          "pinned_position": "CenterCenter",
          "width_pct": "44.86795014742938",
          "height_pct": "46.518377793609346"
        }
      },
      "library_header": {
        "image": {
          "schinese": "40ba56f4964ec808c2abeb3e27ff1ca068aa38bf/library_header_schinese.jpg",
          "english": "d8f4a3b61bf07def68ef77a2aab4d5d1fe8c1ff7/library_header.jpg"
        },
        "image2x": {
          "schinese": "40ba56f4964ec808c2abeb3e27ff1ca068aa38bf/library_header_schinese_2x.jpg",
          "english": "d8f4a3b61bf07def68ef77a2aab4d5d1fe8c1ff7/library_header_2x.jpg"
        }
      }
    },
    "store_asset_mtime": "1761272720",
    "associations": {
      "0": {
        "type": "developer",
        "name": "CLLC Studio"
      },
      "1": {
        "type": "publisher",
        "name": "Spiral Up Games"
      },
      "2": {
        "type": "franchise",
        "name": "Spiral Up Games"
      }
    },
    "primary_genre": "23",
    "genres": {
      "0": "4",
      "1": "23",
      "2": "2"
    },
    "category": {
      "category_2": "1",
      "category_22": "1",
      "category_17": "1",
      "category_23": "1",
      "category_62": "1"
    },
    "supported_languages": {
      "english": {
        "supported": "true",
        "subtitles": "true"
      },
      "japanese": {
        "supported": "true",
        "subtitles": "true"
      },
      "schinese": {
        "supported": "true",
        "subtitles": "true"
      },
      "tchinese": {
        "supported": "true",
        "subtitles": "true"
      }
    },
    "steam_release_date": "1761272418",
    "community_visible_stats": "1",
    "community_hub_visible": "1",
    "gameid": "3371510",
    "store_tags": {
      "0": "1773",
      "1": "32322",
      "2": "3959",
      "3": "492",
      "4": "1716",
      "5": "3871",
      "6": "4182",
      "7": "9",
      "8": "597",
      "9": "1666",
      "10": "5752",
      "11": "1698",
      "12": "6815",
      "13": "4726",
      "14": "17894",
      "15": "4562",
      "16": "1741",
      "17": "4325"
    },
    "review_score": "8",
    "review_percentage": "96"
  },
  "extended": {
    "developer": "CLLC Studio",
    "publisher": "Spiral Up Games"
  },
  "config": {
    "installdir": "RouletteHero",
    "launch": {
      "0": {
        "executable": "RouletteHero.exe"
      },
      "1": {
        "executable": "Mod\\ModTool\\ModEditor\\RouletteHeroEditor.exe",
        "type": "editor",
        "config": {
          "oslist": "windows"
        },
        "description_loc": {
          "english": "ModEditor"
        },
        "description": "ModEditor"
      }
    },
    "steamcontrollertemplateindex": "4",
    "steamdecktouchscreen": "1"
  },
  "depots": {
    "3371511": {
      "manifests": {
        "public": {
          "gid": "758768534857531734",
          "size": "167650403",
          "download": "89396624"
        }
      }
    },
    "baselanguages": "english,schinese,japanese",
    "workshopdepot": "3371510",
    "branches": {
      "public": {
        "buildid": "20573167",
        "timeupdated": "1761655605"
      }
    },
    "privatebranches": "1"
  },
  "ufs": {
    "quota": "102400000",
    "maxnumfiles": "1000",
    "savefiles": {
      "0": {
        "root": "WinAppDataLocalLow",
        "path": "CLLC/RouletteHero",
        "pattern": "*.dat"
      }
    },
    "rootoverrides": {
      "0": {
        "root": "WinAppDataLocalLow",
        "os": "MacOS",
        "oscompare": "=",
        "useinstead": "MacAppSupport",
        "pathtransforms": {
          "0": {
            "find": "CLLC/RouletteHero",
            "replace": "CLLC/RouletteHero"
          }
        }
      },
      "1": {
        "root": "WinAppDataLocalLow",
        "os": "Linux",
        "oscompare": "=",
        "useinstead": "LinuxHome",
        "pathtransforms": {
          "0": {
            "find": "CLLC/RouletteHero",
            "replace": ".config/unity3d/CLLC/RouletteHero"
          }
        }
      }
    }
  }
}