{
  "appid": "3969850",
  "common": {
    "name": "绯红编年史 ~ Chronicle of Scarlet ~ Soundtrack",
    "type": "Music",
    "parent": "3117660",
    "releasestate": "released",
    "oslist": "windows,macos,linux",
    "clienticon": "885cb9d24ca37b59f49d844d2e76ed377c40bbcd",
    "icon": "885cb9d24ca37b59f49d844d2e76ed377c40bbcd",
    "small_capsule": {
      "english": "f24a36ac9aa8aedd281ee101f6875bf609ac63ef/capsule_231x87.jpg",
      "schinese": "f24a36ac9aa8aedd281ee101f6875bf609ac63ef/capsule_231x87_schinese.jpg"
    },
    "header_image": {
      "english": "064e0b9672451b9a6ef81c10e8e8831fca80a089/header.jpg",
      "schinese": "064e0b9672451b9a6ef81c10e8e8831fca80a089/header_schinese.jpg"
    },
    "store_screenshot": "e08e8fb5b7d564dbc1456cec232d6d4dce7f30dc/ss_e08e8fb5b7d564dbc1456cec232d6d4dce7f30dc.jpg",
    "store_asset_mtime": "1756214536",
    "associations": {
      "0": {
        "type": "developer",
        "name": "Charge Piggy Studio"
      },
      "1": {
        "type": "publisher",
        "name": "WindField Games"
      }
    },
    "primary_genre": "0",
    "category": {},
    "steam_release_date": "1759215600",
    "gameid": "3969850",
    "exfgls": "6",
    "store_tags": {}
  },
  "extended": {
    "musicalbumforappid": "3117660",
    "developer": "Charge Piggy Studio",
    "publisher": "WindField Games",
    "musicalbumavailableonstore": "1"
  },
  "config": {
    "installdir": "Chronicle of Scarlet OST"
  },
  "depots": {
    "3969851": {
      "manifests": {
        "public": {
          "gid": "8576530711024709734",
          "size": "120547260",
          "download": "118580656"
        }
      }
    },
    "branches": {
      "public": {
        "buildid": "19887257",
        "timeupdated": "1757242138"
      }
    }
  },
  "albummetadata": {
    "metadata": {
      "artist": {
        "english": "神尾光临,miko",
        "french": "",
        "italian": "",
        "german": "",
        "spanish": "",
        "danish": "",
        "ukrainian": "",
        "russian": "",
        "bulgarian": "",
        "hungarian": "",
        "indonesian": "",
        "turkish": "",
        "greek": "",
        "norwegian": "",
        "czech": "",
        "japanese": "",
        "polish": "",
        "thai": "",
        "swedish": "",
        "schinese": "神尾光临,miko",
        "tchinese": "",
        "romanian": "",
        "finnish": "",
        "dutch": "",
        "brazilian": "",
        "portuguese": "",
        "latam": "",
        "vietnamese": "",
        "koreana": ""
      },
      "composer": {
        "english": "神尾光临",
        "french": "",
        "italian": "",
        "german": "",
        "spanish": "",
        "danish": "",
        "ukrainian": "",
        "russian": "",
        "bulgarian": "",
        "hungarian": "",
        "indonesian": "",
        "turkish": "",
        "greek": "",
        "norwegian": "",
        "czech": "",
        "japanese": "",
        "polish": "",
        "thai": "",
        "swedish": "",
        "schinese": "神尾光临",
        "tchinese": "",
        "romanian": "",
        "finnish": "",
        "dutch": "",
        "brazilian": "",
        "portuguese": "",
        "latam": "",
        "vietnamese": "",
        "koreana": ""
      },
      "label": {
        "english": "Charge Piggy Studio",
        "french": "",
        "italian": "",
        "german": "",
        "spanish": "",
        "danish": "",
        "ukrainian": "",
        "russian": "",
        "bulgarian": "",
        "hungarian": "",
        "indonesian": "",
        "turkish": "",
        "greek": "",
        "norwegian": "",
        "czech": "",
        "japanese": "",
        "polish": "",
        "thai": "",
        "swedish": "",
        "schinese": "冲小猪工作室",
        "tchinese": "",
        "romanian": "",
        "finnish": "",
        "dutch": "",
        "brazilian": "",
        "portuguese": "",
        "latam": "",
        "vietnamese": "",
        "koreana": ""
      },
      "othercredits": {
        "english": "",
        "french": "",
        "italian": "",
        "german": "",
        "spanish": "",
        "danish": "",
        "ukrainian": "",
        "russian": "",
        "bulgarian": "",
        "hungarian": "",
        "indonesian": "",
        "turkish": "",
        "greek": "",
        "norwegian": "",
        "czech": "",
        "japanese": "",
        "polish": "",
        "thai": "",
        "swedish": "",
        "schinese": "",
        "tchinese": "",
        "romanian": "",
        "finnish": "",
        "dutch": "",
        "brazilian": "",
        "portuguese": "",
        "latam": "",
        "vietnamese": "",
        "koreana": ""
      }
    },
    "tracks": {
      "0": {
        "discnumber": "1",
        "tracknumber": "1",
        "originalname": "编年史 -Chronicle-",
        "m": "3",
        "s": "13",
        "internationalname": "Chronicle",
        "languagecode": "zh-cn"
      },
      "1": {
        "discnumber": "1",
        "tracknumber": "2",
        "originalname": "噩梦之始 -Unleash the Nightmare-",
        "m": "1",
        "s": "24",
        "internationalname": "Unleash the Nightmare",
        "languagecode": "zh-cn"
      },
      "2": {
        "discnumber": "1",
        "tracknumber": "3",
        "originalname": "绯色幻想曲 -Rose Fantasia-",
        "m": "2",
        "s": "27",
        "internationalname": "Rose Fantasia",
        "languagecode": "zh-cn"
      },
      "3": {
        "discnumber": "1",
        "tracknumber": "4",
        "originalname": "寒雪之谣 -Snow Cold-",
        "m": "1",
        "s": "49",
        "internationalname": "Snow Cold",
        "languagecode": "zh-cn"
      },
      "4": {
        "discnumber": "1",
        "tracknumber": "5",
        "originalname": "流雨曳藤 -Drifting Wisteria-",
        "m": "5",
        "s": "38",
        "internationalname": "Drifting Wisteria",
        "languagecode": "zh-cn"
      },
      "5": {
        "discnumber": "1",
        "tracknumber": "6",
        "originalname": "魔与塔 -Magictower-",
        "m": "1",
        "s": "22",
        "internationalname": "Magictower",
        "languagecode": "zh-cn"
      },
      "6": {
        "discnumber": "1",
        "tracknumber": "7",
        "originalname": "苍空矩阵 -Sky Matrix-",
        "m": "4",
        "s": "17",
        "internationalname": "Sky Matrix",
        "languagecode": "zh-cn"
      },
      "7": {
        "discnumber": "1",
        "tracknumber": "8",
        "originalname": "杂音 -Noise Severe-",
        "m": "4",
        "s": "42",
        "internationalname": "Noise Severe",
        "languagecode": "zh-cn"
      },
      "8": {
        "discnumber": "1",
        "tracknumber": "9",
        "originalname": "染红教义 -Redder teneT-",
        "m": "5",
        "s": "15",
        "internationalname": "Redder teneT",
        "languagecode": "zh-cn"
      },
      "9": {
        "discnumber": "1",
        "tracknumber": "10",
        "originalname": "亦教红染 -reddeR Tenet-",
        "m": "5",
        "s": "15",
        "internationalname": "reddeR Tenet",
        "languagecode": "zh-cn"
      },
      "10": {
        "discnumber": "1",
        "tracknumber": "11",
        "originalname": "灾夜句点 -Nightsaster-",
        "m": "2",
        "s": "30",
        "internationalname": "Nightsaster",
        "languagecode": "zh-cn"
      },
      "11": {
        "discnumber": "1",
        "tracknumber": "12",
        "originalname": "红月谣 -Crimson Ballad-",
        "m": "2",
        "s": "48",
        "internationalname": "Crimson Ballad",
        "languagecode": "zh-cn"
      },
      "12": {
        "discnumber": "1",
        "tracknumber": "13",
        "originalname": "绯红，编年史 -Chronicle and Scarlet-",
        "m": "2",
        "s": "51",
        "internationalname": "Chronicle and Scarlet",
        "languagecode": "zh-cn"
      },
      "13": {
        "discnumber": "1",
        "tracknumber": "14",
        "originalname": "绯红，编年史 -Chronicle and Scarlet (instrumental)-",
        "m": "2",
        "s": "51",
        "internationalname": "Chronicle and Scarlet (instrumental)",
        "languagecode": "zh-cn"
      },
      "14": {
        "discnumber": "1",
        "tracknumber": "15",
        "originalname": "红楼 -Eastern Dream-",
        "m": "2",
        "s": "34",
        "internationalname": "Eastern Dream",
        "languagecode": "zh-cn"
      }
    },
    "cdn_assets": {
      "album_cover": "4043a1a9b4557d91e8528e1429faa924d2af8131"
    }
  }
}