{
  "appid": "4070650",
  "common": {
    "name": "Angelo Demo",
    "type": "Demo",
    "parent": "3836770",
    "oslist": "windows",
    "osarch": "",
    "osextended": "",
    "icon": "5ea53de27a8a9df803afaa1d91d0778752c08baa",
    "clienticon": "5ea53de27a8a9df803afaa1d91d0778752c08baa",
    "releasestate": "released",
    "small_capsule": {
      "english": "07850ffd5fd0cc12e894446fe2cf4d2da65cd5dd/capsule_231x87.jpg"
    },
    "header_image": {
      "english": "d1164c1d470b0d4faed0fbe7ef343812c555768d/header.jpg"
    },
    "store_asset_mtime": "1759114468",
    "associations": {
      "0": {
        "type": "developer",
        "name": "Yanfer"
      },
      "1": {
        "type": "publisher",
        "name": "Yanfer"
      },
      "2": {
        "type": "franchise",
        "name": "Yanfer"
      }
    },
    "primary_genre": "0",
    "category": {
      "category_75": "1",
      "category_79": "1"
    },
    "gameid": "4070650",
    "exfgls": "6"
  },
  "extended": {
    "developer": "Yanfer",
    "publisher": "Yanfer"
  },
  "config": {
    "installdir": "Angelo Demo",
    "launch": {
      "0": {
        "executable": "ANGELODEMO.exe"
      }
    }
  },
  "depots": {
    "4070651": {
      "manifests": {
        "public": {
          "gid": "3476822074014460281",
          "size": "52876470",
          "download": "39536992"
        }
      }
    },
    "branches": {
      "public": {
        "buildid": "20166631",
        "timeupdated": "1759114100"
      }
    }
  }
}