{
  "appid": "4075810",
  "common": {
    "name": "Paperwork Demo",
    "type": "Demo",
    "parent": "3723530",
    "icon": "8bd7df15fc3e2d0726c3ae05f1364667a5ea3c34",
    "clienticon": "8bd7df15fc3e2d0726c3ae05f1364667a5ea3c34",
    "releasestate": "released",
    "oslist": "windows",
    "osarch": "",
    "osextended": "",
    "small_capsule": {
      "english": "d72f2ba5c840fcd76cf83115c2bffce0d83221d4/capsule_231x87.jpg"
    },
    "header_image": {
      "english": "7249ea6d9ccba2193635932784578f09f846290b/header.jpg"
    },
    "library_assets": {
      "library_capsule": "en",
      "library_hero": "en",
      "library_hero_blur": "en",
      "library_logo": "en",
      "library_header": "en"
    },
    "library_assets_full": {
      "library_capsule": {
        "image": {
          "english": "3536af19156fb46b9b2aff7c12d1a1bf3dbfa199/library_capsule.jpg"
        },
        "image2x": {
          "english": "3536af19156fb46b9b2aff7c12d1a1bf3dbfa199/library_capsule_2x.jpg"
        }
      },
      "library_hero": {
        "image2x": {
          "english": "dd43d10459fb405f935e8273d2cd3301022af7b8/library_hero_2x.jpg"
        },
        "image": {
          "english": "dd43d10459fb405f935e8273d2cd3301022af7b8/library_hero.jpg"
        }
      },
      "library_hero_blur": {
        "image": {
          "english": "dd43d10459fb405f935e8273d2cd3301022af7b8/library_hero_blur.jpg"
        }
      },
      "library_logo": {
        "image": {
          "english": "584e7c5fef252c12260de398577c48d4d22e3056/logo.png"
        },
        "image2x": {
          "english": "584e7c5fef252c12260de398577c48d4d22e3056/logo_2x.png"
        }
      },
      "library_header": {
        "image": {
          "english": "c6aeb5197bee28a3d8576383a38068ba26b86c6b/library_header.jpg"
        },
        "image2x": {
          "english": "c6aeb5197bee28a3d8576383a38068ba26b86c6b/library_header_2x.jpg"
        }
      }
    },
    "store_asset_mtime": "1759851172",
    "associations": {
      "0": {
        "type": "developer",
        "name": "Broken Record Studio"
      },
      "1": {
        "type": "publisher",
        "name": "Broken Record Studio"
      }
    },
    "primary_genre": "0",
    "category": {
      "category_68": "1",
      "category_74": "1",
      "category_79": "1"
    },
    "steam_release_date": "1759755656",
    "gameid": "4075810",
    "exfgls": "6"
  },
  "extended": {
    "developer": "Broken Record Studio",
    "publisher": "Broken Record Studio"
  },
  "config": {
    "installdir": "Paperwork Demo",
    "launch": {
      "0": {
        "executable": "Paperwork.exe",
        "type": "default",
        "config": {
          "oslist": "windows"
        }
      }
    }
  },
  "depots": {
    "4075811": {
      "manifests": {
        "public": {
          "gid": "4138246619801851756",
          "size": "414151547",
          "download": "128021488"
        }
      }
    },
    "branches": {
      "public": {
        "buildid": "20234714",
        "timeupdated": "1759475828"
      }
    }
  }
}