{
  "appid": "871270",
  "common": {
    "name": "Wild West VR",
    "type": "Game",
    "releasestate": "released",
    "controllervr": {
      "steamvr": "1"
    },
    "playareavr": {
      "seated": "1",
      "standing": "1"
    },
    "oslist": "windows",
    "osarch": "",
    "clienttga": "a4b73bbcbcab24f4b3d3c3c94182856b642c80c1",
    "clienticon": "579e02550ac1b2e225000d2ab9eccf5805056900",
    "icon": "9d8917bb5ff5306c1a5f712a24ca2763eeb5d9b4",
    "logo": "53ec16997921f10f526ac2ee89f00634ae25e513",
    "logo_small": "53ec16997921f10f526ac2ee89f00634ae25e513_thumb",
    "eulas": {
      "0": {
        "id": "871270_eula_0",
        "name": "Wild West VR EULA",
        "url": "https://store.steampowered.com//eula/871270_eula_0"
      }
    },
    "openvrsupport": "1",
    "restricted_countries": "DE",
    "metacritic_name": "Wild West VR",
    "small_capsule": {
      "english": "capsule_231x87.jpg"
    },
    "header_image": {
      "english": "header.jpg"
    },
    "store_screenshot": "ss_9595b7036646f7a65e6bd20925d07d054cccf1b3.jpg",
    "store_asset_mtime": "1527062174",
    "associations": {
      "0": {
        "type": "developer",
        "name": "VironIT"
      },
      "1": {
        "type": "publisher",
        "name": "VironIT"
      }
    },
    "primary_genre": "1",
    "genres": {
      "0": "1"
    },
    "category": {
      "category_2": "1",
      "category_52": "1",
      "category_54": "1"
    },
    "supported_languages": {
      "english": {
        "supported": "true",
        "full_audio": "true"
      }
    },
    "original_release_date": "1528959600",
    "steam_release_date": "1529048523",
    "community_hub_visible": "1",
    "gameid": "871270",
    "exfgls": "3",
    "onlyvrsupport": "1",
    "store_tags": {
      "0": "19",
      "1": "21978"
    },
    "review_score": "5",
    "review_percentage": "50"
  },
  "extended": {
    "vrheadsetstreaming": "1",
    "developer": "VironIT",
    "publisher": "VironIT",
    "isfreeapp": "1"
  },
  "config": {
    "installdir": "Wild West VR",
    "launch": {
      "0": {
        "executable": "WildWestVR.exe",
        "type": "vr",
        "config": {
          "oslist": "windows"
        }
      }
    },
    "noupdatesafterinstall": "1"
  },
  "depots": {
    "871271": {
      "config": {
        "oslist": "windows"
      },
      "manifests": {
        "public": {
          "gid": "5373986083071338427",
          "size": "276631989",
          "download": "86146624"
        }
      }
    },
    "hasdepotsindlc": "0",
    "baselanguages": "english",
    "branches": {
      "public": {
        "buildid": "2799207",
        "timeupdated": "1527072622"
      }
    }
  }
}